magma_orc8r_client/orchestrator.py
magma_orc8r_client/endpoints/base_endpoint.py
magma_orc8r_client/endpoints/lte.py
magma_orc8r_client/schemas/aggregated_maximum_bitrate.py
magma_orc8r_client/schemas/aggregation_logging_configs.py
magma_orc8r_client/schemas/apn.py
magma_orc8r_client/schemas/apn_configuration.py
magma_orc8r_client/schemas/apn_name.py
magma_orc8r_client/schemas/apn_resource.py
magma_orc8r_client/schemas/apn_resources.py
magma_orc8r_client/schemas/arp.py
magma_orc8r_client/schemas/base_name.py
magma_orc8r_client/schemas/base_name_record.py
magma_orc8r_client/schemas/base_names.py
magma_orc8r_client/schemas/cellular_gateway_pool.py
magma_orc8r_client/schemas/cellular_gateway_pool_configs.py
magma_orc8r_client/schemas/cellular_gateway_pool_record.py
magma_orc8r_client/schemas/cellular_gateway_pool_records.py
magma_orc8r_client/schemas/challenge_key.py
magma_orc8r_client/schemas/channel_id.py
magma_orc8r_client/schemas/config_info.py
magma_orc8r_client/schemas/disk_partition.py
magma_orc8r_client/schemas/dns_config_record.py
magma_orc8r_client/schemas/elastic_hit.py
magma_orc8r_client/schemas/elastic_hit_count.py
magma_orc8r_client/schemas/email_receiver.py
magma_orc8r_client/schemas/enodeb.py
magma_orc8r_client/schemas/enodeb_config.py
magma_orc8r_client/schemas/enodeb_configuration.py
magma_orc8r_client/schemas/enodeb_serials.py
magma_orc8r_client/schemas/enodeb_state.py
magma_orc8r_client/schemas/error.py
magma_orc8r_client/schemas/event.py
magma_orc8r_client/schemas/feg_network_id.py
magma_orc8r_client/schemas/flow_description.py
magma_orc8r_client/schemas/flow_match.py
magma_orc8r_client/schemas/flow_qos.py
magma_orc8r_client/schemas/gateway_cellular_configs.py
magma_orc8r_client/schemas/gateway_description.py
magma_orc8r_client/schemas/gateway_device.py
magma_orc8r_client/schemas/gateway_dns_configs.py
magma_orc8r_client/schemas/gateway_dns_records.py
magma_orc8r_client/schemas/gateway_epc_configs.py
magma_orc8r_client/schemas/gateway_he_config.py
magma_orc8r_client-1.0.4.dist-info/METADATA
magma_orc8r_client-1.0.4.dist-info/WHEEL
magma_orc8r_client-1.0.4.dist-info/top_level.txt
magma_orc8r_client-1.0.4.dist-info/RECORD
