Metadata-Version: 2.1
Name: magma-orc8r-client
Version: 1.0.4
Summary: A simple client to communicate with Magma Orchestrator
Author-email: Guillaume Belanger <guillaume.belanger27@gmail.com>
Project-URL: Homepage, https://github.com/gruyaume/magma-orc8r-client
Keywords: 5G,4G,Magma,Core,Network
Classifier: License :: OSI Approved :: Apache Software License
Classifier: Programming Language :: Python
Classifier: Programming Language :: Python :: 3
Requires-Python: >=3.8
Requires-Dist: feedparser (>=5.2.0)
Requires-Dist: html2text
Requires-Dist: pydantic
Requires-Dist: cryptography
Requires-Dist: requests
Requires-Dist: tomli ; python_version < "3.11"
